LICENCE
flake8_print.py
pyproject.toml
flake8_print-4.0.1.dist-info/entry_points.txt
flake8_print-4.0.1.dist-info/WHEEL
flake8_print-4.0.1.dist-info/METADATA
flake8_print-4.0.1.dist-info/RECORD
